ggviz/__init__.py
ggviz-0.0.0a0.dist-info/WHEEL
ggviz-0.0.0a0.dist-info/METADATA
ggviz-0.0.0a0.dist-info/RECORD
